LICENSE
MANIFEST.in
README.md
setup.cfg
setup.py
versioneer.py
cvnn/__init__.py
cvnn/__main__.py
cvnn/_version.py
cvnn/activations.py
cvnn/cli.py
cvnn/initializers.py
cvnn/losses.py
cvnn/metrics.py
cvnn/real_equiv_tools.py
cvnn/tb.py
cvnn/utils.py
cvnn.egg-info/PKG-INFO
cvnn.egg-info/SOURCES.txt
cvnn.egg-info/dependency_links.txt
cvnn.egg-info/entry_points.txt
cvnn.egg-info/requires.txt
cvnn.egg-info/top_level.txt
cvnn/layers/__init__.py
cvnn/layers/convolutional.py
cvnn/layers/core.py
cvnn/layers/pooling.py
cvnn/layers/upsampling.py