Metadata-Version: 2.1
Name: cvnn
Version: 1.2.18
Summary: Library to help implement a complex-valued neural network (cvnn) using tensorflow as back-end
Home-page: https://github.com/NEGU93/cvnn
Author: J Agustin BARRACHINA
Author-email: joseagustin.barra@gmail.com
License: MIT
Keywords: cvnn
Platform: UNKNOWN
Classifier: Programming Language :: Python :: 2.7
Classifier: Programming Language :: Python :: 3.6
Classifier: Programming Language :: Python :: 3.7
Provides-Extra: plotter
Provides-Extra: full
